{
  "CachePath": "./cache",
  "inputJsonFile": "ADO_TESTProjPipline_V03.json",
  "targetAccessToken": null,
  "targetOrganization": "nkdagility-preview",
  "targetProject": "ABB-Demo",
  "targetParentId": 540,
  "templateAccessToken": null,
  "templateOrganization": "ABB-MO-ATE",
  "templateProject": "ABB Traction Template",
  "templateParentId": 212315,
  "targetQuery": "SELECT [System.Id], [System.WorkItemType], [System.Title], [System.AreaPath],[System.AssignedTo],[System.State] FROM workitems WHERE [System.Parent] = @projectID",
  "targetQueryTitle": "Project-@RunName - @projectTitle",
  "targetQueryFolder": "Shared Queries"

}
